setup.py
thot
v4l2capture.c
src/thotus/__init__.py
src/thotus/cloudify.py
src/thotus/commands.py
src/thotus/main.py
src/thotus/settings.py
src/thotus/ui.py
src/thotus.egg-info/PKG-INFO
src/thotus.egg-info/SOURCES.txt
src/thotus.egg-info/dependency_links.txt
src/thotus.egg-info/requires.txt
src/thotus.egg-info/top_level.txt
src/thotus/algorithms/__init__.py
src/thotus/algorithms/algo_pureimage.py
src/thotus/algorithms/algo_straightpureimage.py
src/thotus/algorithms/algo_straightuncanny.py
src/thotus/algorithms/algo_uncanny.py
src/thotus/algorithms/projection.py
src/thotus/algorithms/ransac.py
src/thotus/algorithms/utils.py
src/thotus/boards/__init__.py
src/thotus/boards/ciclop/__init__.py
src/thotus/boards/ciclop/board.py
src/thotus/boards/dummy/__init__.py
src/thotus/boards/dummy/board.py
src/thotus/calibration/__init__.py
src/thotus/calibration/camera.py
src/thotus/calibration/chessboard.py
src/thotus/calibration/data.py
src/thotus/calibration/lasers.py
src/thotus/calibration/platform.py
src/thotus/camera/__init__.py
src/thotus/camera/v4l2.py
src/thotus/mesh/__init__.py
src/thotus/mesh/model.py
src/thotus/mesh/ply.py