Metadata-Version: 1.1
Name: thotus
Version: 0.1.1
Summary: A 3D scanning application
Home-page: https://github.com/fdev31/thot
Author: Fabien Devaux
Author-email: fdev31@gmail.com
License: MIT
Platform: UNKNOWN
Classifier: Environment :: Console
Classifier: Development Status :: 4 - Beta
Classifier: Programming Language :: Python :: 2.7
Classifier: Programming Language :: Python :: 3
Classifier: Programming Language :: Python :: 3.1
Classifier: Programming Language :: Python :: 3.2
Classifier: Programming Language :: Python :: 3.3
Classifier: Programming Language :: Python :: 3.4
